weclappy.py
weclappy-0.3.1.dist-info/METADATA
weclappy-0.3.1.dist-info/WHEEL
weclappy-0.3.1.dist-info/top_level.txt
weclappy-0.3.1.dist-info/RECORD
