Metadata-Version: 2.4
Name: weclappy
Version: 0.3.1
Summary: A Python client for the Weclapp API.
Author-email: Markus Wals <markus@wals.pro>
License: MIT
Project-URL: Homepage, https://wals.pro/
Project-URL: Repository, https://github.com/Wals-pro/weclappy
Project-URL: Documentation, https://github.com/Wals-pro/weclappy#readme
Classifier: Programming Language :: Python :: 3
Classifier: License :: OSI Approved :: MIT License
Classifier: Operating System :: OS Independent
Requires-Dist: requests>=2.26.0
